courtvision/config.py
courtvision/console.py
courtvision/data.py
courtvision/geometry.py
courtvision/models.py
courtvision/pipeline.py
courtvision/swiss.py
courtvision/trackers.py
courtvision/trainer.py
courtvision/vis.py
courtvision-0.2.0.dist-info/LICENSE
courtvision-0.2.0.dist-info/METADATA
courtvision-0.2.0.dist-info/WHEEL
courtvision-0.2.0.dist-info/entry_points.txt
courtvision-0.2.0.dist-info/RECORD
